fluentassert/__init__.py
fluentassert/exceptions.py
fluentassert/assertions_check/__init__.py
fluentassert/assertions_check/booleans.py
fluentassert/assertions_check/collections.py
fluentassert/assertions_check/dicts.py
fluentassert/assertions_check/geo.py
fluentassert/assertions_check/lists.py
fluentassert/assertions_check/numbers.py
fluentassert/assertions_check/sequences.py
fluentassert/assertions_check/strings.py
fluentassert/assertions_check/types.py
fluentassert/assertions_check/uuids.py
fluentassert/assertions_is/__init__.py
fluentassert/assertions_is/base_is.py
fluentassert/assertions_is/booleans.py
fluentassert/assertions_is/collections.py
fluentassert/assertions_is/dicts.py
fluentassert/assertions_is/emptiness.py
fluentassert/assertions_is/geo.py
fluentassert/assertions_is/lists.py
fluentassert/assertions_is/numbers.py
fluentassert/assertions_is/sequences.py
fluentassert/assertions_is/strings.py
fluentassert/assertions_is/types.py
fluentassert/assertions_is/uuids.py
fluentassert/classes/__init__.py
fluentassert/classes/check.py
fluentassert/classes/is_cls.py
fluentassert/tests/__init__.py
fluentassert/tests/tests_check/__init__.py
fluentassert/tests/tests_check/test_basic_checks.py
fluentassert/tests/tests_check/test_booleans.py
fluentassert/tests/tests_check/test_collections.py
fluentassert/tests/tests_check/test_dicts.py
fluentassert/tests/tests_check/test_file_formats.py
fluentassert/tests/tests_check/test_geo.py
fluentassert/tests/tests_check/test_numbers.py
fluentassert/tests/tests_check/test_sequences.py
fluentassert/tests/tests_check/test_strings.py
fluentassert/tests/tests_check/test_type_hierarchy.py
fluentassert/tests/tests_check/test_uuids.py
fluentassert/tests/tests_is/__init__.py
fluentassert/tests/tests_is/test_basic_checks_is.py
fluentassert/tests/tests_is/test_booleans_is.py
fluentassert/tests/tests_is/test_chain_closure_is.py
fluentassert/tests/tests_is/test_collections_is.py
fluentassert/tests/tests_is/test_dicts_is.py
fluentassert-0.0.7.dist-info/LICENSE
fluentassert-0.0.7.dist-info/METADATA
fluentassert-0.0.7.dist-info/WHEEL
fluentassert-0.0.7.dist-info/top_level.txt
fluentassert-0.0.7.dist-info/RECORD
