Metadata-Version: 2.1
Name: fluentassert
Version: 0.0.7
Summary: Fluent assertions framework for Python
Home-page: https://github.com/sheikhjebran/fluentassert
Author: Sheikh Jebran
Author-email: sheikhjebran@gmail.com
License: MIT License
Keywords: check python fluent fluent-interface assertion-library assertions testing fluent-assertions fluentcheck
Platform: UNKNOWN
Classifier: License :: OSI Approved :: MIT License
Classifier: Programming Language :: Python :: 3 :: Only
Classifier: Natural Language :: English
Classifier: Operating System :: OS Independent
Classifier: Development Status :: 4 - Beta
Classifier: Intended Audience :: Developers
Classifier: Topic :: Software Development :: Libraries
Requires-Python: >3.5.0
License-File: LICENSE
Requires-Dist: pyyaml (>=4.2b1)
